{"edges": [{"source": "BB004b5ba0", "target": "BB004b5c68", "attributes": {"type": "consequence"}}, {"source": "BB004b5ba0", "target": "BB004b5bbd", "attributes": {"type": "alternative"}}, {"source": "BB004b5bbd", "target": "BB004b5c0c", "attributes": {"type": "consequence"}}, {"source": "BB004b5bbd", "target": "BB004b5bc4", "attributes": {"type": "alternative"}}, {"source": "BB004b5bc4", "target": "BB004b5c18", "attributes": {"type": "consequence"}}, {"source": "BB004b5bc4", "target": "BB004b5bc9", "attributes": {"type": "alternative"}}, {"source": "BB004b5bc9", "target": "BB004b5bee", "attributes": {"type": "alternative"}}, {"source": "BB004b5bee", "target": "BB004b5c00", "attributes": {"type": "consequence"}}, {"source": "BB004b5bee", "target": "BB004b5bf2", "attributes": {"type": "alternative"}}, {"source": "BB004b5c00", "target": "BB004b5c31", "attributes": {"type": "consequence"}}, {"source": "BB004b5c00", "target": "BB004b5c08", "attributes": {"type": "alternative"}}, {"source": "BB004b5c08", "target": "BB004b5c0c", "attributes": {"type": "regular"}}, {"source": "BB004b5c18", "target": "BB004b5c31", "attributes": {"type": "regular"}}, {"source": "BB004b5c31", "target": "BB004b5bf2", "attributes": {"type": "consequence"}}, {"source": "BB004b5c31", "target": "BB004b5c5b", "attributes": {"type": "alternative"}}, {"source": "BB004b5c5b", "target": "BB004b5c0c", "attributes": {"type": "regular"}}, {"source": "BB004b5c68", "target": "BB004b5bee", "attributes": {"type": "regular"}}], "nodes": [{"attributes": {"lines": 10}, "key": "BB004b5c31"}, {"attributes": {"lines": 3}, "key": "BB004b5bf2"}, {"attributes": {"lines": 3}, "key": "BB004b5bbd"}, {"attributes": {"lines": 5}, "key": "BB004b5c18"}, {"attributes": {"lines": 2}, "key": "BB004b5c5b"}, {"attributes": {"lines": 2}, "key": "BB004b5bc4"}, {"attributes": {"lines": 6}, "key": "BB004b5ba0"}, {"attributes": {"lines": 3}, "key": "BB004b5c00"}, {"attributes": {"lines": 3}, "key": "BB004b5c0c"}, {"attributes": {"lines": 2}, "key": "BB004b5bee"}, {"attributes": {"lines": 8}, "key": "BB004b5c68"}, {"attributes": {"lines": 1}, "key": "BB004b5c08"}, {"attributes": {"lines": 8}, "key": "BB004b5bc9"}], "options": {"type": "directed", "multi": true, "allowSelfLoops": true}, "attributes": {}}