{"edges": [{"source": "BB00558220", "target": "BB00558278", "attributes": {"type": "consequence"}}, {"source": "BB00558220", "target": "BB0055822b", "attributes": {"type": "alternative"}}, {"source": "BB0055822b", "target": "BB00558246", "attributes": {"type": "consequence"}}, {"source": "BB0055822b", "target": "BB00558236", "attributes": {"type": "alternative"}}, {"source": "BB00558236", "target": "BB00558268", "attributes": {"type": "consequence"}}, {"source": "BB00558236", "target": "BB00558246", "attributes": {"type": "alternative"}}, {"source": "BB00558246", "target": "BB0055825e", "attributes": {"type": "alternative"}}, {"source": "BB00558278", "target": "BB0055825e", "attributes": {"type": "regular"}}], "nodes": [{"attributes": {"lines": 4}, "key": "BB0055822b"}, {"attributes": {"lines": 5}, "key": "BB00558268"}, {"attributes": {"lines": 5}, "key": "BB00558220"}, {"attributes": {"lines": 4}, "key": "BB00558246"}, {"attributes": {"lines": 12}, "key": "BB00558278"}, {"attributes": {"lines": 4}, "key": "BB0055825e"}, {"attributes": {"lines": 5}, "key": "BB00558236"}], "options": {"type": "directed", "multi": true, "allowSelfLoops": true}, "attributes": {}}