{
  "attributes": {}, 
  "edges": [
    {
      "attributes": {
        "type": "consequence"
      }, 
      "source": "BB00552a60", 
      "target": "BB00552ac0"
    }, 
    {
      "attributes": {
        "type": "alternative"
      }, 
      "source": "BB00552a60", 
      "target": "BB00552a6a"
    }, 
    {
      "attributes": {
        "type": "consequence"
      }, 
      "source": "BB00552a6a", 
      "target": "BB00552ac0"
    }, 
    {
      "attributes": {
        "type": "alternative"
      }, 
      "source": "BB00552a6a", 
      "target": "BB00552a6f"
    }, 
    {
      "attributes": {
        "type": "consequence"
      }, 
      "source": "BB00552a6f", 
      "target": "BB00552a90"
    }, 
    {
      "attributes": {
        "type": "alternative"
      }, 
      "source": "BB00552a6f", 
      "target": "BB00552a7a"
    }, 
    {
      "attributes": {
        "type": "alternative"
      }, 
      "source": "BB00552a7a", 
      "target": "BB00552a87"
    }, 
    {
      "attributes": {
        "type": "consequence"
      }, 
      "source": "BB00552a90", 
      "target": "BB00552b20"
    }, 
    {
      "attributes": {
        "type": "alternative"
      }, 
      "source": "BB00552a90", 
      "target": "BB00552aa5"
    }, 
    {
      "attributes": {
        "type": "consequence"
      }, 
      "source": "BB00552aa5", 
      "target": "BB00552b00"
    }, 
    {
      "attributes": {
        "type": "alternative"
      }, 
      "source": "BB00552aa5", 
      "target": "BB00552ab3"
    }, 
    {
      "attributes": {
        "type": "regular"
      }, 
      "source": "BB00552b00", 
      "target": "BB00552a87"
    }, 
    {
      "attributes": {
        "type": "regular"
      }, 
      "source": "BB00552b20", 
      "target": "BB00552a87"
    }
  ], 
  "nodes": [
    {
      "attributes": {
        "lines": 2
      }, 
      "key": "BB00552a6a"
    }, 
    {
      "attributes": {
        "lines": 4
      }, 
      "key": "BB00552a6f"
    }, 
    {
      "attributes": {
        "lines": 4
      }, 
      "key": "BB00552a60"
    }, 
    {
      "attributes": {
        "lines": 14
      }, 
      "key": "BB00552ac0"
    }, 
    {
      "attributes": {
        "lines": 2
      }, 
      "key": "BB00552b20"
    }, 
    {
      "attributes": {
        "lines": 6
      }, 
      "key": "BB00552b00"
    }, 
    {
      "attributes": {
        "lines": 3
      }, 
      "key": "BB00552a87"
    }, 
    {
      "attributes": {
        "lines": 4
      }, 
      "key": "BB00552aa5"
    }, 
    {
      "attributes": {
        "lines": 4
      }, 
      "key": "BB00552a7a"
    }, 
    {
      "attributes": {
        "lines": 4
      }, 
      "key": "BB00552ab3"
    }, 
    {
      "attributes": {
        "lines": 6
      }, 
      "key": "BB00552a90"
    }
  ], 
  "options": {
    "allowSelfLoops": true, 
    "multi": true, 
    "type": "directed"
  }
}