{
  "attributes": {}, 
  "edges": [
    {
      "attributes": {
        "type": "consequence"
      }, 
      "source": "BB00552ec0", 
      "target": "BB00552fa0"
    }, 
    {
      "attributes": {
        "type": "alternative"
      }, 
      "source": "BB00552ec0", 
      "target": "BB00552ed4"
    }, 
    {
      "attributes": {
        "type": "consequence"
      }, 
      "source": "BB00552ed4", 
      "target": "BB00552fa8"
    }, 
    {
      "attributes": {
        "type": "alternative"
      }, 
      "source": "BB00552ed4", 
      "target": "BB00552ef5"
    }, 
    {
      "attributes": {
        "type": "consequence"
      }, 
      "source": "BB00552ef5", 
      "target": "BB00552f78"
    }, 
    {
      "attributes": {
        "type": "alternative"
      }, 
      "source": "BB00552ef5", 
      "target": "BB00552f06"
    }, 
    {
      "attributes": {
        "type": "consequence"
      }, 
      "source": "BB00552f06", 
      "target": "BB00552f1c"
    }, 
    {
      "attributes": {
        "type": "alternative"
      }, 
      "source": "BB00552f06", 
      "target": "BB00552f0b"
    }, 
    {
      "attributes": {
        "type": "consequence"
      }, 
      "source": "BB00552f0b", 
      "target": "BB00552f78"
    }, 
    {
      "attributes": {
        "type": "alternative"
      }, 
      "source": "BB00552f0b", 
      "target": "BB00552f1c"
    }, 
    {
      "attributes": {
        "type": "consequence"
      }, 
      "source": "BB00552f1c", 
      "target": "BB00552f32"
    }, 
    {
      "attributes": {
        "type": "alternative"
      }, 
      "source": "BB00552f1c", 
      "target": "BB00552f21"
    }, 
    {
      "attributes": {
        "type": "consequence"
      }, 
      "source": "BB00552f21", 
      "target": "BB00552f78"
    }, 
    {
      "attributes": {
        "type": "alternative"
      }, 
      "source": "BB00552f21", 
      "target": "BB00552f32"
    }, 
    {
      "attributes": {
        "type": "consequence"
      }, 
      "source": "BB00552f32", 
      "target": "BB00552f78"
    }, 
    {
      "attributes": {
        "type": "alternative"
      }, 
      "source": "BB00552f32", 
      "target": "BB00552f46"
    }, 
    {
      "attributes": {
        "type": "regular"
      }, 
      "source": "BB00552fa0", 
      "target": "BB00552f32"
    }
  ], 
  "nodes": [
    {
      "attributes": {
        "lines": 5
      }, 
      "key": "BB00552f0b"
    }, 
    {
      "attributes": {
        "lines": 8
      }, 
      "key": "BB00552fa8"
    }, 
    {
      "attributes": {
        "lines": 7
      }, 
      "key": "BB00552ec0"
    }, 
    {
      "attributes": {
        "lines": 2
      }, 
      "key": "BB00552fa0"
    }, 
    {
      "attributes": {
        "lines": 5
      }, 
      "key": "BB00552f21"
    }, 
    {
      "attributes": {
        "lines": 2
      }, 
      "key": "BB00552f06"
    }, 
    {
      "attributes": {
        "lines": 13
      }, 
      "key": "BB00552f46"
    }, 
    {
      "attributes": {
        "lines": 11
      }, 
      "key": "BB00552f78"
    }, 
    {
      "attributes": {
        "lines": 2
      }, 
      "key": "BB00552f1c"
    }, 
    {
      "attributes": {
        "lines": 5
      }, 
      "key": "BB00552f32"
    }, 
    {
      "attributes": {
        "lines": 8
      }, 
      "key": "BB00552ed4"
    }, 
    {
      "attributes": {
        "lines": 5
      }, 
      "key": "BB00552ef5"
    }
  ], 
  "options": {
    "allowSelfLoops": true, 
    "multi": true, 
    "type": "directed"
  }
}