{"edges": [{"source": "BB005a3690", "target": "BB005a3700", "attributes": {"type": "consequence"}}, {"source": "BB005a3690", "target": "BB005a369c", "attributes": {"type": "alternative"}}, {"source": "BB005a369c", "target": "BB005a36e8", "attributes": {"type": "consequence"}}, {"source": "BB005a369c", "target": "BB005a36af", "attributes": {"type": "alternative"}}, {"source": "BB005a36af", "target": "BB005a36c4", "attributes": {"type": "consequence"}}, {"source": "BB005a36af", "target": "BB005a36bb", "attributes": {"type": "alternative"}}, {"source": "BB005a36bb", "target": "BB005a36c4", "attributes": {"type": "regular"}}, {"source": "BB005a36c4", "target": "BB005a36d8", "attributes": {"type": "alternative"}}, {"source": "BB005a3700", "target": "BB005a36d8", "attributes": {"type": "regular"}}], "nodes": [{"attributes": {"lines": 4}, "key": "BB005a36c4"}, {"attributes": {"lines": 12}, "key": "BB005a3700"}, {"attributes": {"lines": 3}, "key": "BB005a36af"}, {"attributes": {"lines": 6}, "key": "BB005a36e8"}, {"attributes": {"lines": 5}, "key": "BB005a3690"}, {"attributes": {"lines": 5}, "key": "BB005a369c"}, {"attributes": {"lines": 5}, "key": "BB005a36d8"}, {"attributes": {"lines": 1}, "key": "BB005a36bb"}], "options": {"type": "directed", "multi": true, "allowSelfLoops": true}, "attributes": {}}