{
  "attributes": {}, 
  "edges": [
    {
      "attributes": {
        "type": "consequence"
      }, 
      "source": "BB005b2300", 
      "target": "BB005b2618"
    }, 
    {
      "attributes": {
        "type": "alternative"
      }, 
      "source": "BB005b2300", 
      "target": "BB005b230e"
    }, 
    {
      "attributes": {
        "type": "consequence"
      }, 
      "source": "BB005b230e", 
      "target": "BB005b2560"
    }, 
    {
      "attributes": {
        "type": "alternative"
      }, 
      "source": "BB005b230e", 
      "target": "BB005b2321"
    }, 
    {
      "attributes": {
        "type": "consequence"
      }, 
      "source": "BB005b2321", 
      "target": "BB005b2450"
    }, 
    {
      "attributes": {
        "type": "alternative"
      }, 
      "source": "BB005b2321", 
      "target": "BB005b232c"
    }, 
    {
      "attributes": {
        "type": "consequence"
      }, 
      "source": "BB005b232c", 
      "target": "BB005b2450"
    }, 
    {
      "attributes": {
        "type": "alternative"
      }, 
      "source": "BB005b232c", 
      "target": "BB005b2336"
    }, 
    {
      "attributes": {
        "type": "consequence"
      }, 
      "source": "BB005b2336", 
      "target": "BB005b26e0"
    }, 
    {
      "attributes": {
        "type": "alternative"
      }, 
      "source": "BB005b2336", 
      "target": "BB005b2344"
    }, 
    {
      "attributes": {
        "type": "consequence"
      }, 
      "source": "BB005b2344", 
      "target": "BB005b236a"
    }, 
    {
      "attributes": {
        "type": "alternative"
      }, 
      "source": "BB005b2344", 
      "target": "BB005b2349"
    }, 
    {
      "attributes": {
        "type": "consequence"
      }, 
      "source": "BB005b2349", 
      "target": "BB005b2548"
    }, 
    {
      "attributes": {
        "type": "alternative"
      }, 
      "source": "BB005b2349", 
      "target": "BB005b235b"
    }, 
    {
      "attributes": {
        "type": "alternative"
      }, 
      "source": "BB005b235b", 
      "target": "BB005b236a"
    }, 
    {
      "attributes": {
        "type": "consequence"
      }, 
      "source": "BB005b236a", 
      "target": "BB005b25c8"
    }, 
    {
      "attributes": {
        "type": "alternative"
      }, 
      "source": "BB005b236a", 
      "target": "BB005b2379"
    }, 
    {
      "attributes": {
        "type": "consequence"
      }, 
      "source": "BB005b2379", 
      "target": "BB005b2396"
    }, 
    {
      "attributes": {
        "type": "alternative"
      }, 
      "source": "BB005b2379", 
      "target": "BB005b237e"
    }, 
    {
      "attributes": {
        "type": "consequence"
      }, 
      "source": "BB005b237e", 
      "target": "BB005b2396"
    }, 
    {
      "attributes": {
        "type": "alternative"
      }, 
      "source": "BB005b237e", 
      "target": "BB005b2385"
    }, 
    {
      "attributes": {
        "type": "consequence"
      }, 
      "source": "BB005b2385", 
      "target": "BB005b2670"
    }, 
    {
      "attributes": {
        "type": "alternative"
      }, 
      "source": "BB005b2385", 
      "target": "BB005b2396"
    }, 
    {
      "attributes": {
        "type": "consequence"
      }, 
      "source": "BB005b2396", 
      "target": "BB005b23ef"
    }, 
    {
      "attributes": {
        "type": "alternative"
      }, 
      "source": "BB005b2396", 
      "target": "BB005b23e4"
    }, 
    {
      "attributes": {
        "type": "consequence"
      }, 
      "source": "BB005b23e4", 
      "target": "BB005b23ef"
    }, 
    {
      "attributes": {
        "type": "alternative"
      }, 
      "source": "BB005b23e4", 
      "target": "BB005b23eb"
    }, 
    {
      "attributes": {
        "type": "regular"
      }, 
      "source": "BB005b23eb", 
      "target": "BB005b23ef"
    }, 
    {
      "attributes": {
        "type": "consequence"
      }, 
      "source": "BB005b23ef", 
      "target": "BB005b2411"
    }, 
    {
      "attributes": {
        "type": "alternative"
      }, 
      "source": "BB005b23ef", 
      "target": "BB005b23f9"
    }, 
    {
      "attributes": {
        "type": "consequence"
      }, 
      "source": "BB005b23f9", 
      "target": "BB005b2758"
    }, 
    {
      "attributes": {
        "type": "alternative"
      }, 
      "source": "BB005b23f9", 
      "target": "BB005b2411"
    }, 
    {
      "attributes": {
        "type": "consequence"
      }, 
      "source": "BB005b2411", 
      "target": "BB005b243a"
    }, 
    {
      "attributes": {
        "type": "alternative"
      }, 
      "source": "BB005b2411", 
      "target": "BB005b2428"
    }, 
    {
      "attributes": {
        "type": "consequence"
      }, 
      "source": "BB005b2428", 
      "target": "BB005b2690"
    }, 
    {
      "attributes": {
        "type": "alternative"
      }, 
      "source": "BB005b2428", 
      "target": "BB005b243a"
    }, 
    {
      "attributes": {
        "type": "regular"
      }, 
      "source": "BB005b243a", 
      "target": "BB005b2440"
    }, 
    {
      "attributes": {
        "type": "consequence"
      }, 
      "source": "BB005b2450", 
      "target": "BB005b246f"
    }, 
    {
      "attributes": {
        "type": "alternative"
      }, 
      "source": "BB005b2450", 
      "target": "BB005b245a"
    }, 
    {
      "attributes": {
        "type": "consequence"
      }, 
      "source": "BB005b245a", 
      "target": "BB005b2720"
    }, 
    {
      "attributes": {
        "type": "alternative"
      }, 
      "source": "BB005b245a", 
      "target": "BB005b246a"
    }, 
    {
      "attributes": {
        "type": "regular"
      }, 
      "source": "BB005b246a", 
      "target": "BB005b246f"
    }, 
    {
      "attributes": {
        "type": "consequence"
      }, 
      "source": "BB005b246f", 
      "target": "BB005b2650"
    }, 
    {
      "attributes": {
        "type": "alternative"
      }, 
      "source": "BB005b246f", 
      "target": "BB005b247c"
    }, 
    {
      "attributes": {
        "type": "consequence"
      }, 
      "source": "BB005b247c", 
      "target": "BB005b2500"
    }, 
    {
      "attributes": {
        "type": "alternative"
      }, 
      "source": "BB005b247c", 
      "target": "BB005b24d5"
    }, 
    {
      "attributes": {
        "type": "consequence"
      }, 
      "source": "BB005b24d5", 
      "target": "BB005b2500"
    }, 
    {
      "attributes": {
        "type": "alternative"
      }, 
      "source": "BB005b24d5", 
      "target": "BB005b24e0"
    }, 
    {
      "attributes": {
        "type": "consequence"
      }, 
      "source": "BB005b24e0", 
      "target": "BB005b2770"
    }, 
    {
      "attributes": {
        "type": "alternative"
      }, 
      "source": "BB005b24e0", 
      "target": "BB005b24ec"
    }, 
    {
      "attributes": {
        "type": "regular"
      }, 
      "source": "BB005b24ec", 
      "target": "BB005b24f0"
    }, 
    {
      "attributes": {
        "type": "alternative"
      }, 
      "source": "BB005b24f0", 
      "target": "BB005b2500"
    }, 
    {
      "attributes": {
        "type": "consequence"
      }, 
      "source": "BB005b2500", 
      "target": "BB005b2525"
    }, 
    {
      "attributes": {
        "type": "alternative"
      }, 
      "source": "BB005b2500", 
      "target": "BB005b2513"
    }, 
    {
      "attributes": {
        "type": "consequence"
      }, 
      "source": "BB005b2513", 
      "target": "BB005b26d0"
    }, 
    {
      "attributes": {
        "type": "alternative"
      }, 
      "source": "BB005b2513", 
      "target": "BB005b2525"
    }, 
    {
      "attributes": {
        "type": "consequence"
      }, 
      "source": "BB005b2525", 
      "target": "BB005b243a"
    }, 
    {
      "attributes": {
        "type": "alternative"
      }, 
      "source": "BB005b2525", 
      "target": "BB005b2536"
    }, 
    {
      "attributes": {
        "type": "regular"
      }, 
      "source": "BB005b2548", 
      "target": "BB005b235b"
    }, 
    {
      "attributes": {
        "type": "consequence"
      }, 
      "source": "BB005b2560", 
      "target": "BB005b256a"
    }, 
    {
      "attributes": {
        "type": "alternative"
      }, 
      "source": "BB005b2560", 
      "target": "BB005b2565"
    }, 
    {
      "attributes": {
        "type": "alternative"
      }, 
      "source": "BB005b2565", 
      "target": "BB005b256a"
    }, 
    {
      "attributes": {
        "type": "consequence"
      }, 
      "source": "BB005b256a", 
      "target": "BB005b258b"
    }, 
    {
      "attributes": {
        "type": "alternative"
      }, 
      "source": "BB005b256a", 
      "target": "BB005b2573"
    }, 
    {
      "attributes": {
        "type": "consequence"
      }, 
      "source": "BB005b2573", 
      "target": "BB005b258b"
    }, 
    {
      "attributes": {
        "type": "alternative"
      }, 
      "source": "BB005b2573", 
      "target": "BB005b257a"
    }, 
    {
      "attributes": {
        "type": "consequence"
      }, 
      "source": "BB005b257a", 
      "target": "BB005b2680"
    }, 
    {
      "attributes": {
        "type": "alternative"
      }, 
      "source": "BB005b257a", 
      "target": "BB005b258b"
    }, 
    {
      "attributes": {
        "type": "regular"
      }, 
      "source": "BB005b258b", 
      "target": "BB005b2411"
    }, 
    {
      "attributes": {
        "type": "regular"
      }, 
      "source": "BB005b25c8", 
      "target": "BB005b23ef"
    }, 
    {
      "attributes": {
        "type": "regular"
      }, 
      "source": "BB005b2618", 
      "target": "BB005b2440"
    }, 
    {
      "attributes": {
        "type": "regular"
      }, 
      "source": "BB005b2650", 
      "target": "BB005b247c"
    }, 
    {
      "attributes": {
        "type": "regular"
      }, 
      "source": "BB005b2670", 
      "target": "BB005b2396"
    }, 
    {
      "attributes": {
        "type": "regular"
      }, 
      "source": "BB005b2680", 
      "target": "BB005b258b"
    }, 
    {
      "attributes": {
        "type": "regular"
      }, 
      "source": "BB005b2690", 
      "target": "BB005b2440"
    }, 
    {
      "attributes": {
        "type": "regular"
      }, 
      "source": "BB005b26d0", 
      "target": "BB005b2440"
    }, 
    {
      "attributes": {
        "type": "alternative"
      }, 
      "source": "BB005b26e0", 
      "target": "BB005b26f1"
    }, 
    {
      "attributes": {
        "type": "alternative"
      }, 
      "source": "BB005b26f1", 
      "target": "BB005b2710"
    }, 
    {
      "attributes": {
        "type": "regular"
      }, 
      "source": "BB005b2710", 
      "target": "BB005b2440"
    }, 
    {
      "attributes": {
        "type": "regular"
      }, 
      "source": "BB005b2720", 
      "target": "BB005b2440"
    }, 
    {
      "attributes": {
        "type": "regular"
      }, 
      "source": "BB005b2758", 
      "target": "BB005b26f1"
    }, 
    {
      "attributes": {
        "type": "consequence"
      }, 
      "source": "BB005b2770", 
      "target": "BB005b2710"
    }, 
    {
      "attributes": {
        "type": "alternative"
      }, 
      "source": "BB005b2770", 
      "target": "BB005b2790"
    }, 
    {
      "attributes": {
        "type": "regular"
      }, 
      "source": "BB005b2790", 
      "target": "BB005b24f0"
    }
  ], 
  "nodes": [
    {
      "attributes": {
        "lines": 2
      }, 
      "key": "BB005b2344"
    }, 
    {
      "attributes": {
        "lines": 5
      }, 
      "key": "BB005b2440"
    }, 
    {
      "attributes": {
        "lines": 4
      }, 
      "key": "BB005b2548"
    }, 
    {
      "attributes": {
        "lines": 13
      }, 
      "key": "BB005b25c8"
    }, 
    {
      "attributes": {
        "lines": 4
      }, 
      "key": "BB005b2349"
    }, 
    {
      "attributes": {
        "lines": 4
      }, 
      "key": "BB005b24d5"
    }, 
    {
      "attributes": {
        "lines": 3
      }, 
      "key": "BB005b2450"
    }, 
    {
      "attributes": {
        "lines": 5
      }, 
      "key": "BB005b2650"
    }, 
    {
      "attributes": {
        "lines": 4
      }, 
      "key": "BB005b26d0"
    }, 
    {
      "attributes": {
        "lines": 4
      }, 
      "key": "BB005b2758"
    }, 
    {
      "attributes": {
        "lines": 4
      }, 
      "key": "BB005b245a"
    }, 
    {
      "attributes": {
        "lines": 4
      }, 
      "key": "BB005b235b"
    }, 
    {
      "attributes": {
        "lines": 3
      }, 
      "key": "BB005b23e4"
    }, 
    {
      "attributes": {
        "lines": 1
      }, 
      "key": "BB005b2565"
    }, 
    {
      "attributes": {
        "lines": 3
      }, 
      "key": "BB005b26e0"
    }, 
    {
      "attributes": {
        "lines": 2
      }, 
      "key": "BB005b2560"
    }, 
    {
      "attributes": {
        "lines": 3
      }, 
      "key": "BB005b24e0"
    }, 
    {
      "attributes": {
        "lines": 1
      }, 
      "key": "BB005b24ec"
    }, 
    {
      "attributes": {
        "lines": 3
      }, 
      "key": "BB005b23ef"
    }, 
    {
      "attributes": {
        "lines": 3
      }, 
      "key": "BB005b246f"
    }, 
    {
      "attributes": {
        "lines": 3
      }, 
      "key": "BB005b236a"
    }, 
    {
      "attributes": {
        "lines": 1
      }, 
      "key": "BB005b246a"
    }, 
    {
      "attributes": {
        "lines": 3
      }, 
      "key": "BB005b256a"
    }, 
    {
      "attributes": {
        "lines": 1
      }, 
      "key": "BB005b23eb"
    }, 
    {
      "attributes": {
        "lines": 2
      }, 
      "key": "BB005b2670"
    }, 
    {
      "attributes": {
        "lines": 8
      }, 
      "key": "BB005b2770"
    }, 
    {
      "attributes": {
        "lines": 4
      }, 
      "key": "BB005b24f0"
    }, 
    {
      "attributes": {
        "lines": 7
      }, 
      "key": "BB005b26f1"
    }, 
    {
      "attributes": {
        "lines": 3
      }, 
      "key": "BB005b2573"
    }, 
    {
      "attributes": {
        "lines": 19
      }, 
      "key": "BB005b247c"
    }, 
    {
      "attributes": {
        "lines": 3
      }, 
      "key": "BB005b237e"
    }, 
    {
      "attributes": {
        "lines": 2
      }, 
      "key": "BB005b2379"
    }, 
    {
      "attributes": {
        "lines": 5
      }, 
      "key": "BB005b23f9"
    }, 
    {
      "attributes": {
        "lines": 5
      }, 
      "key": "BB005b257a"
    }, 
    {
      "attributes": {
        "lines": 5
      }, 
      "key": "BB005b2385"
    }, 
    {
      "attributes": {
        "lines": 5
      }, 
      "key": "BB005b2300"
    }, 
    {
      "attributes": {
        "lines": 5
      }, 
      "key": "BB005b2500"
    }, 
    {
      "attributes": {
        "lines": 2
      }, 
      "key": "BB005b2680"
    }, 
    {
      "attributes": {
        "lines": 5
      }, 
      "key": "BB005b230e"
    }, 
    {
      "attributes": {
        "lines": 11
      }, 
      "key": "BB005b258b"
    }, 
    {
      "attributes": {
        "lines": 15
      }, 
      "key": "BB005b2396"
    }, 
    {
      "attributes": {
        "lines": 14
      }, 
      "key": "BB005b2690"
    }, 
    {
      "attributes": {
        "lines": 2
      }, 
      "key": "BB005b2710"
    }, 
    {
      "attributes": {
        "lines": 3
      }, 
      "key": "BB005b2790"
    }, 
    {
      "attributes": {
        "lines": 6
      }, 
      "key": "BB005b2411"
    }, 
    {
      "attributes": {
        "lines": 4
      }, 
      "key": "BB005b2513"
    }, 
    {
      "attributes": {
        "lines": 12
      }, 
      "key": "BB005b2618"
    }, 
    {
      "attributes": {
        "lines": 4
      }, 
      "key": "BB005b2525"
    }, 
    {
      "attributes": {
        "lines": 11
      }, 
      "key": "BB005b2720"
    }, 
    {
      "attributes": {
        "lines": 2
      }, 
      "key": "BB005b2321"
    }, 
    {
      "attributes": {
        "lines": 2
      }, 
      "key": "BB005b232c"
    }, 
    {
      "attributes": {
        "lines": 4
      }, 
      "key": "BB005b2428"
    }, 
    {
      "attributes": {
        "lines": 2
      }, 
      "key": "BB005b2336"
    }, 
    {
      "attributes": {
        "lines": 6
      }, 
      "key": "BB005b2536"
    }, 
    {
      "attributes": {
        "lines": 1
      }, 
      "key": "BB005b243a"
    }
  ], 
  "options": {
    "allowSelfLoops": true, 
    "multi": true, 
    "type": "directed"
  }
}