{"edges": [{"source": "BB005b3f60", "target": "BB005b4070", "attributes": {"type": "consequence"}}, {"source": "BB005b3f60", "target": "BB005b3f92", "attributes": {"type": "alternative"}}, {"source": "BB005b3f92", "target": "BB005b4000", "attributes": {"type": "consequence"}}, {"source": "BB005b3f92", "target": "BB005b3fb5", "attributes": {"type": "alternative"}}, {"source": "BB005b3fb5", "target": "BB005b40c0", "attributes": {"type": "consequence"}}, {"source": "BB005b3fb5", "target": "BB005b3fbe", "attributes": {"type": "alternative"}}, {"source": "BB005b3fbe", "target": "BB005b401c", "attributes": {"type": "consequence"}}, {"source": "BB005b3fbe", "target": "BB005b3fd6", "attributes": {"type": "alternative"}}, {"source": "BB005b3fd6", "target": "BB005b3fdd", "attributes": {"type": "regular"}}, {"source": "BB005b3fdd", "target": "BB005b4031", "attributes": {"type": "consequence"}}, {"source": "BB005b3fdd", "target": "BB005b3fee", "attributes": {"type": "alternative"}}, {"source": "BB005b4000", "target": "BB005b40b0", "attributes": {"type": "consequence"}}, {"source": "BB005b4000", "target": "BB005b401c", "attributes": {"type": "alternative"}}, {"source": "BB005b401c", "target": "BB005b3fee", "attributes": {"type": "consequence"}}, {"source": "BB005b401c", "target": "BB005b4031", "attributes": {"type": "alternative"}}, {"source": "BB005b40b0", "target": "BB005b3fdd", "attributes": {"type": "regular"}}, {"source": "BB005b40c0", "target": "BB005b3fdd", "attributes": {"type": "consequence"}}, {"source": "BB005b40c0", "target": "BB005b40de", "attributes": {"type": "alternative"}}, {"source": "BB005b40de", "target": "BB005b3fd6", "attributes": {"type": "regular"}}], "nodes": [{"attributes": {"lines": 15}, "key": "BB005b3f60"}, {"attributes": {"lines": 5}, "key": "BB005b4000"}, {"attributes": {"lines": 6}, "key": "BB005b40c0"}, {"attributes": {"lines": 7}, "key": "BB005b3fee"}, {"attributes": {"lines": 2}, "key": "BB005b3fb5"}, {"attributes": {"lines": 1}, "key": "BB005b3fd6"}, {"attributes": {"lines": 18}, "key": "BB005b4070"}, {"attributes": {"lines": 2}, "key": "BB005b40b0"}, {"attributes": {"lines": 18}, "key": "BB005b4031"}, {"attributes": {"lines": 11}, "key": "BB005b3f92"}, {"attributes": {"lines": 4}, "key": "BB005b401c"}, {"attributes": {"lines": 4}, "key": "BB005b3fdd"}, {"attributes": {"lines": 5}, "key": "BB005b3fbe"}, {"attributes": {"lines": 1}, "key": "BB005b40de"}], "options": {"type": "directed", "multi": true, "allowSelfLoops": true}, "attributes": {}}