{"edges": [{"source": "BB0064c770", "target": "BB0064c7c2", "attributes": {"type": "consequence"}}, {"source": "BB0064c770", "target": "BB0064c7b3", "attributes": {"type": "alternative"}}, {"source": "BB0064c7b3", "target": "BB0064c7c2", "attributes": {"type": "alternative"}}, {"source": "BB0064c7c2", "target": "BB0064c7f0", "attributes": {"type": "consequence"}}, {"source": "BB0064c7c2", "target": "BB0064c7eb", "attributes": {"type": "alternative"}}, {"source": "BB0064c7eb", "target": "BB0064c7f0", "attributes": {"type": "alternative"}}], "nodes": [{"attributes": {"lines": 3}, "key": "BB0064c7b3"}, {"attributes": {"lines": 19}, "key": "BB0064c770"}, {"attributes": {"lines": 5}, "key": "BB0064c7f0"}, {"attributes": {"lines": 1}, "key": "BB0064c7eb"}, {"attributes": {"lines": 10}, "key": "BB0064c7c2"}], "options": {"type": "directed", "multi": true, "allowSelfLoops": true}, "attributes": {}}