{"edges": [{"source": "BB00689f00", "target": "BB00689f70", "attributes": {"type": "consequence"}}, {"source": "BB00689f00", "target": "BB00689f05", "attributes": {"type": "alternative"}}, {"source": "BB00689f05", "target": "BB00689f69", "attributes": {"type": "consequence"}}, {"source": "BB00689f05", "target": "BB00689f45", "attributes": {"type": "alternative"}}, {"source": "BB00689f45", "target": "BB00689f69", "attributes": {"type": "alternative"}}], "nodes": [{"attributes": {"lines": 2}, "key": "BB00689f70"}, {"attributes": {"lines": 14}, "key": "BB00689f05"}, {"attributes": {"lines": 8}, "key": "BB00689f45"}, {"attributes": {"lines": 2}, "key": "BB00689f00"}, {"attributes": {"lines": 4}, "key": "BB00689f69"}], "options": {"type": "directed", "multi": true, "allowSelfLoops": true}, "attributes": {}}