{
  "attributes": {}, 
  "edges": [
    {
      "attributes": {
        "type": "consequence"
      }, 
      "source": "BB0082e240", 
      "target": "BB0082e24b"
    }, 
    {
      "attributes": {
        "type": "alternative"
      }, 
      "source": "BB0082e240", 
      "target": "BB0082e249"
    }, 
    {
      "attributes": {
        "type": "consequence"
      }, 
      "source": "BB0082e24b", 
      "target": "BB0082e6a0"
    }, 
    {
      "attributes": {
        "type": "alternative"
      }, 
      "source": "BB0082e24b", 
      "target": "BB0082e277"
    }, 
    {
      "attributes": {
        "type": "consequence"
      }, 
      "source": "BB0082e277", 
      "target": "BB0082e670"
    }, 
    {
      "attributes": {
        "type": "alternative"
      }, 
      "source": "BB0082e277", 
      "target": "BB0082e29b"
    }, 
    {
      "attributes": {
        "type": "consequence"
      }, 
      "source": "BB0082e29b", 
      "target": "BB0082e400"
    }, 
    {
      "attributes": {
        "type": "alternative"
      }, 
      "source": "BB0082e29b", 
      "target": "BB0082e2a6"
    }, 
    {
      "attributes": {
        "type": "consequence"
      }, 
      "source": "BB0082e2a6", 
      "target": "BB0082e2f0"
    }, 
    {
      "attributes": {
        "type": "alternative"
      }, 
      "source": "BB0082e2a6", 
      "target": "BB0082e2b0"
    }, 
    {
      "attributes": {
        "type": "regular"
      }, 
      "source": "BB0082e2b0", 
      "target": "BB0082e2b3"
    }, 
    {
      "attributes": {
        "type": "consequence"
      }, 
      "source": "BB0082e2b3", 
      "target": "BB0082e2b3"
    }, 
    {
      "attributes": {
        "type": "alternative"
      }, 
      "source": "BB0082e2b3", 
      "target": "BB0082e2dd"
    }, 
    {
      "attributes": {
        "type": "regular"
      }, 
      "source": "BB0082e2dd", 
      "target": "BB0082e2f0"
    }, 
    {
      "attributes": {
        "type": "consequence"
      }, 
      "source": "BB0082e2f0", 
      "target": "BB0082e2f0"
    }, 
    {
      "attributes": {
        "type": "alternative"
      }, 
      "source": "BB0082e2f0", 
      "target": "BB0082e3f0"
    }, 
    {
      "attributes": {
        "type": "consequence"
      }, 
      "source": "BB0082e3f0", 
      "target": "BB0082e670"
    }, 
    {
      "attributes": {
        "type": "alternative"
      }, 
      "source": "BB0082e3f0", 
      "target": "BB0082e3fa"
    }, 
    {
      "attributes": {
        "type": "regular"
      }, 
      "source": "BB0082e3fa", 
      "target": "BB0082e890"
    }, 
    {
      "attributes": {
        "type": "consequence"
      }, 
      "source": "BB0082e400", 
      "target": "BB0082e670"
    }, 
    {
      "attributes": {
        "type": "alternative"
      }, 
      "source": "BB0082e400", 
      "target": "BB0082e40d"
    }, 
    {
      "attributes": {
        "type": "consequence"
      }, 
      "source": "BB0082e40d", 
      "target": "BB0082e448"
    }, 
    {
      "attributes": {
        "type": "alternative"
      }, 
      "source": "BB0082e40d", 
      "target": "BB0082e413"
    }, 
    {
      "attributes": {
        "type": "regular"
      }, 
      "source": "BB0082e413", 
      "target": "BB0082e416"
    }, 
    {
      "attributes": {
        "type": "consequence"
      }, 
      "source": "BB0082e416", 
      "target": "BB0082e416"
    }, 
    {
      "attributes": {
        "type": "alternative"
      }, 
      "source": "BB0082e416", 
      "target": "BB0082e440"
    }, 
    {
      "attributes": {
        "type": "regular"
      }, 
      "source": "BB0082e440", 
      "target": "BB0082e448"
    }, 
    {
      "attributes": {
        "type": "regular"
      }, 
      "source": "BB0082e448", 
      "target": "BB0082e4a6"
    }, 
    {
      "attributes": {
        "type": "regular"
      }, 
      "source": "BB0082e470", 
      "target": "BB0082e4a6"
    }, 
    {
      "attributes": {
        "type": "consequence"
      }, 
      "source": "BB0082e4a6", 
      "target": "BB0082e470"
    }, 
    {
      "attributes": {
        "type": "alternative"
      }, 
      "source": "BB0082e4a6", 
      "target": "BB0082e645"
    }, 
    {
      "attributes": {
        "type": "consequence"
      }, 
      "source": "BB0082e645", 
      "target": "BB0082e670"
    }, 
    {
      "attributes": {
        "type": "alternative"
      }, 
      "source": "BB0082e645", 
      "target": "BB0082e663"
    }, 
    {
      "attributes": {
        "type": "regular"
      }, 
      "source": "BB0082e663", 
      "target": "BB0082e890"
    }, 
    {
      "attributes": {
        "type": "consequence"
      }, 
      "source": "BB0082e670", 
      "target": "BB0082e670"
    }, 
    {
      "attributes": {
        "type": "alternative"
      }, 
      "source": "BB0082e670", 
      "target": "BB0082e69a"
    }, 
    {
      "attributes": {
        "type": "regular"
      }, 
      "source": "BB0082e69a", 
      "target": "BB0082e890"
    }, 
    {
      "attributes": {
        "type": "consequence"
      }, 
      "source": "BB0082e6a0", 
      "target": "BB0082e850"
    }, 
    {
      "attributes": {
        "type": "alternative"
      }, 
      "source": "BB0082e6a0", 
      "target": "BB0082e6b6"
    }, 
    {
      "attributes": {
        "type": "regular"
      }, 
      "source": "BB0082e6b6", 
      "target": "BB0082e6c0"
    }, 
    {
      "attributes": {
        "type": "consequence"
      }, 
      "source": "BB0082e6c0", 
      "target": "BB0082e6ea"
    }, 
    {
      "attributes": {
        "type": "alternative"
      }, 
      "source": "BB0082e6c0", 
      "target": "BB0082e6e7"
    }, 
    {
      "attributes": {
        "type": "regular"
      }, 
      "source": "BB0082e6e7", 
      "target": "BB0082e6ea"
    }, 
    {
      "attributes": {
        "type": "consequence"
      }, 
      "source": "BB0082e6ea", 
      "target": "BB0082e715"
    }, 
    {
      "attributes": {
        "type": "alternative"
      }, 
      "source": "BB0082e6ea", 
      "target": "BB0082e712"
    }, 
    {
      "attributes": {
        "type": "regular"
      }, 
      "source": "BB0082e712", 
      "target": "BB0082e715"
    }, 
    {
      "attributes": {
        "type": "consequence"
      }, 
      "source": "BB0082e715", 
      "target": "BB0082e740"
    }, 
    {
      "attributes": {
        "type": "alternative"
      }, 
      "source": "BB0082e715", 
      "target": "BB0082e73d"
    }, 
    {
      "attributes": {
        "type": "regular"
      }, 
      "source": "BB0082e73d", 
      "target": "BB0082e740"
    }, 
    {
      "attributes": {
        "type": "consequence"
      }, 
      "source": "BB0082e740", 
      "target": "BB0082e76b"
    }, 
    {
      "attributes": {
        "type": "alternative"
      }, 
      "source": "BB0082e740", 
      "target": "BB0082e768"
    }, 
    {
      "attributes": {
        "type": "regular"
      }, 
      "source": "BB0082e768", 
      "target": "BB0082e76b"
    }, 
    {
      "attributes": {
        "type": "consequence"
      }, 
      "source": "BB0082e76b", 
      "target": "BB0082e796"
    }, 
    {
      "attributes": {
        "type": "alternative"
      }, 
      "source": "BB0082e76b", 
      "target": "BB0082e793"
    }, 
    {
      "attributes": {
        "type": "regular"
      }, 
      "source": "BB0082e793", 
      "target": "BB0082e796"
    }, 
    {
      "attributes": {
        "type": "consequence"
      }, 
      "source": "BB0082e796", 
      "target": "BB0082e7c1"
    }, 
    {
      "attributes": {
        "type": "alternative"
      }, 
      "source": "BB0082e796", 
      "target": "BB0082e7be"
    }, 
    {
      "attributes": {
        "type": "regular"
      }, 
      "source": "BB0082e7be", 
      "target": "BB0082e7c1"
    }, 
    {
      "attributes": {
        "type": "consequence"
      }, 
      "source": "BB0082e7c1", 
      "target": "BB0082e7ec"
    }, 
    {
      "attributes": {
        "type": "alternative"
      }, 
      "source": "BB0082e7c1", 
      "target": "BB0082e7e9"
    }, 
    {
      "attributes": {
        "type": "regular"
      }, 
      "source": "BB0082e7e9", 
      "target": "BB0082e7ec"
    }, 
    {
      "attributes": {
        "type": "consequence"
      }, 
      "source": "BB0082e7ec", 
      "target": "BB0082e817"
    }, 
    {
      "attributes": {
        "type": "alternative"
      }, 
      "source": "BB0082e7ec", 
      "target": "BB0082e814"
    }, 
    {
      "attributes": {
        "type": "regular"
      }, 
      "source": "BB0082e814", 
      "target": "BB0082e817"
    }, 
    {
      "attributes": {
        "type": "consequence"
      }, 
      "source": "BB0082e817", 
      "target": "BB0082e6c0"
    }, 
    {
      "attributes": {
        "type": "alternative"
      }, 
      "source": "BB0082e817", 
      "target": "BB0082e843"
    }, 
    {
      "attributes": {
        "type": "consequence"
      }, 
      "source": "BB0082e843", 
      "target": "BB0082e850"
    }, 
    {
      "attributes": {
        "type": "alternative"
      }, 
      "source": "BB0082e843", 
      "target": "BB0082e849"
    }, 
    {
      "attributes": {
        "type": "regular"
      }, 
      "source": "BB0082e849", 
      "target": "BB0082e890"
    }, 
    {
      "attributes": {
        "type": "consequence"
      }, 
      "source": "BB0082e850", 
      "target": "BB0082e850"
    }, 
    {
      "attributes": {
        "type": "alternative"
      }, 
      "source": "BB0082e850", 
      "target": "BB0082e88d"
    }, 
    {
      "attributes": {
        "type": "regular"
      }, 
      "source": "BB0082e88d", 
      "target": "BB0082e890"
    }
  ], 
  "nodes": [
    {
      "attributes": {
        "lines": 2
      }, 
      "key": "BB0082e29b"
    }, 
    {
      "attributes": {
        "lines": 1
      }, 
      "key": "BB0082e69a"
    }, 
    {
      "attributes": {
        "lines": 12
      }, 
      "key": "BB0082e715"
    }, 
    {
      "attributes": {
        "lines": 1
      }, 
      "key": "BB0082e814"
    }, 
    {
      "attributes": {
        "lines": 10
      }, 
      "key": "BB0082e817"
    }, 
    {
      "attributes": {
        "lines": 13
      }, 
      "key": "BB0082e416"
    }, 
    {
      "attributes": {
        "lines": 12
      }, 
      "key": "BB0082e796"
    }, 
    {
      "attributes": {
        "lines": 8
      }, 
      "key": "BB0082e890"
    }, 
    {
      "attributes": {
        "lines": 1
      }, 
      "key": "BB0082e413"
    }, 
    {
      "attributes": {
        "lines": 1
      }, 
      "key": "BB0082e793"
    }, 
    {
      "attributes": {
        "lines": 1
      }, 
      "key": "BB0082e712"
    }, 
    {
      "attributes": {
        "lines": 2
      }, 
      "key": "BB0082e40d"
    }, 
    {
      "attributes": {
        "lines": 1
      }, 
      "key": "BB0082e88d"
    }, 
    {
      "attributes": {
        "lines": 2
      }, 
      "key": "BB0082e400"
    }, 
    {
      "attributes": {
        "lines": 1
      }, 
      "key": "BB0082e73d"
    }, 
    {
      "attributes": {
        "lines": 1
      }, 
      "key": "BB0082e7be"
    }, 
    {
      "attributes": {
        "lines": 1
      }, 
      "key": "BB0082e6b6"
    }, 
    {
      "attributes": {
        "lines": 1
      }, 
      "key": "BB0082e2b0"
    }, 
    {
      "attributes": {
        "lines": 13
      }, 
      "key": "BB0082e2b3"
    }, 
    {
      "attributes": {
        "lines": 3
      }, 
      "key": "BB0082e2a6"
    }, 
    {
      "attributes": {
        "lines": 129
      }, 
      "key": "BB0082e4a6"
    }, 
    {
      "attributes": {
        "lines": 4
      }, 
      "key": "BB0082e6a0"
    }, 
    {
      "attributes": {
        "lines": 2
      }, 
      "key": "BB0082e2dd"
    }, 
    {
      "attributes": {
        "lines": 17
      }, 
      "key": "BB0082e850"
    }, 
    {
      "attributes": {
        "lines": 1
      }, 
      "key": "BB0082e249"
    }, 
    {
      "attributes": {
        "lines": 1
      }, 
      "key": "BB0082e849"
    }, 
    {
      "attributes": {
        "lines": 12
      }, 
      "key": "BB0082e448"
    }, 
    {
      "attributes": {
        "lines": 13
      }, 
      "key": "BB0082e24b"
    }, 
    {
      "attributes": {
        "lines": 7
      }, 
      "key": "BB0082e645"
    }, 
    {
      "attributes": {
        "lines": 12
      }, 
      "key": "BB0082e7c1"
    }, 
    {
      "attributes": {
        "lines": 3
      }, 
      "key": "BB0082e240"
    }, 
    {
      "attributes": {
        "lines": 3
      }, 
      "key": "BB0082e440"
    }, 
    {
      "attributes": {
        "lines": 11
      }, 
      "key": "BB0082e6c0"
    }, 
    {
      "attributes": {
        "lines": 12
      }, 
      "key": "BB0082e740"
    }, 
    {
      "attributes": {
        "lines": 2
      }, 
      "key": "BB0082e843"
    }, 
    {
      "attributes": {
        "lines": 1
      }, 
      "key": "BB0082e3fa"
    }, 
    {
      "attributes": {
        "lines": 8
      }, 
      "key": "BB0082e277"
    }, 
    {
      "attributes": {
        "lines": 2
      }, 
      "key": "BB0082e3f0"
    }, 
    {
      "attributes": {
        "lines": 73
      }, 
      "key": "BB0082e2f0"
    }, 
    {
      "attributes": {
        "lines": 13
      }, 
      "key": "BB0082e670"
    }, 
    {
      "attributes": {
        "lines": 15
      }, 
      "key": "BB0082e470"
    }, 
    {
      "attributes": {
        "lines": 12
      }, 
      "key": "BB0082e7ec"
    }, 
    {
      "attributes": {
        "lines": 1
      }, 
      "key": "BB0082e7e9"
    }, 
    {
      "attributes": {
        "lines": 1
      }, 
      "key": "BB0082e768"
    }, 
    {
      "attributes": {
        "lines": 12
      }, 
      "key": "BB0082e76b"
    }, 
    {
      "attributes": {
        "lines": 12
      }, 
      "key": "BB0082e6ea"
    }, 
    {
      "attributes": {
        "lines": 1
      }, 
      "key": "BB0082e6e7"
    }, 
    {
      "attributes": {
        "lines": 1
      }, 
      "key": "BB0082e663"
    }
  ], 
  "options": {
    "allowSelfLoops": true, 
    "multi": true, 
    "type": "directed"
  }
}